odoo10_addon_partner_noncommercial-10.0.1.0.0.99.dev8-nspkg.pth
odoo/addons/partner_noncommercial/README.rst
odoo/addons/partner_noncommercial/__init__.py
odoo/addons/partner_noncommercial/__manifest__.py
odoo/addons/partner_noncommercial/i18n/nl.po
odoo/addons/partner_noncommercial/i18n/partner_noncommercial.pot
odoo/addons/partner_noncommercial/i18n/sl.po
odoo/addons/partner_noncommercial/i18n_extra/en.po
odoo/addons/partner_noncommercial/i18n_extra/nl.po
odoo/addons/partner_noncommercial/static/description/icon.png
odoo/addons/partner_noncommercial/views/menu.xml
odoo/addons/partner_noncommercial/views/res_partner.xml
odoo10_addon_partner_noncommercial-10.0.1.0.0.99.dev8.dist-info/METADATA
odoo10_addon_partner_noncommercial-10.0.1.0.0.99.dev8.dist-info/WHEEL
odoo10_addon_partner_noncommercial-10.0.1.0.0.99.dev8.dist-info/namespace_packages.txt
odoo10_addon_partner_noncommercial-10.0.1.0.0.99.dev8.dist-info/top_level.txt
odoo10_addon_partner_noncommercial-10.0.1.0.0.99.dev8.dist-info/RECORD
